fastmixture/__init__.py
fastmixture/em.cpython-311-darwin.so
fastmixture/functions.py
fastmixture/main.py
fastmixture/shared.cpython-311-darwin.so
fastmixture/svd.cpython-311-darwin.so
fastmixture-0.93.3.dist-info/LICENSE
fastmixture-0.93.3.dist-info/METADATA
fastmixture-0.93.3.dist-info/WHEEL
fastmixture-0.93.3.dist-info/entry_points.txt
fastmixture-0.93.3.dist-info/top_level.txt
fastmixture-0.93.3.dist-info/RECORD
