Metadata-Version: 2.1
Name: fastmixture
Version: 0.93.3
Summary: Fast Ancestry Estimation
Home-page: https://github.com/Rosemeis/fastmixture
Author: Jonas Meisner
Author-email: meisnerucph@gmail.com
Classifier: Programming Language :: Python :: 3
Classifier: License :: OSI Approved :: GNU General Public License v3 (GPLv3)
Classifier: Operating System :: OS Independent
Classifier: Development Status :: 4 - Beta
Requires-Python: >=3.7
License-File: LICENSE
Requires-Dist: cython >3.0.0
Requires-Dist: numpy >2.0.0
